Comparator/main.v
module compare(a,b,gt,lt,eq,ge,le);

    input wire[63:0] a,b;
    output wire gt,lt,eq,ge,le;

    assign gt= (a>b);
    assign lt= (a<b);
    assign eq= (a===b);
    assign ge= (a>=b);
    assign le= (a<=b);

endmodule

Comparator/TB.sv
`include "main.v"
module tb;

    reg [63:0] a,b;

    wire[4:0] out;

    compare dut(a,b,out[0],out[1],out[2],out[3],out[4]);

    initial begin
       repeat(20) begin
            a<=$random;
            b<=$random;
            #5;
        end
        $finish();
    end

    initial begin
        $monitor("%d %d || %b",dut.a,dut.b,out);
        $dumpfile("tb.vcd");
        $dumpvars(0,tb);
    end

endmodule

Comparator/tb.vcd
$date
	Fri Apr 05 21:56:03 2024
$end
$version
	ModelSim Version 2020.1
$end
$timescale
	1ps
$end

$scope module tb $end
$var reg 64 ! a [63:0] $end
$var reg 64 " b [63:0] $end
$var wire 1 # out [4] $end
$var wire 1 $ out [3] $end
$var wire 1 % out [2] $end
$var wire 1 & out [1] $end
$var wire 1 ' out [0] $end

$scope module dut $end
$var wire 1 ( a [63] $end
$var wire 1 ) a [62] $end
$var wire 1 * a [61] $end
$var wire 1 + a [60] $end
$var wire 1 , a [59] $end
$var wire 1 - a [58] $end
$var wire 1 . a [57] $end
$var wire 1 / a [56] $end
$var wire 1 0 a [55] $end
$var wire 1 1 a [54] $end
$var wire 1 2 a [53] $end
$var wire 1 3 a [52] $end
$var wire 1 4 a [51] $end
$var wire 1 5 a [50] $end
$var wire 1 6 a [49] $end
$var wire 1 7 a [48] $end
$var wire 1 8 a [47] $end
$var wire 1 9 a [46] $end
$var wire 1 : a [45] $end
$var wire 1 ; a [44] $end
$var wire 1 < a [43] $end
$var wire 1 = a [42] $end
$var wire 1 > a [41] $end
$var wire 1 ? a [40] $end
$var wire 1 @ a [39] $end
$var wire 1 A a [38] $end
$var wire 1 B a [37] $end
$var wire 1 C a [36] $end
$var wire 1 D a [35] $end
$var wire 1 E a [34] $end
$var wire 1 F a [33] $end
$var wire 1 G a [32] $end
$var wire 1 H a [31] $end
$var wire 1 I a [30] $end
$var wire 1 J a [29] $end
$var wire 1 K a [28] $end
$var wire 1 L a [27] $end
$var wire 1 M a [26] $end
$var wire 1 N a [25] $end
$var wire 1 O a [24] $end
$var wire 1 P a [23] $end
$var wire 1 Q a [22] $end
$var wire 1 R a [21] $end
$var wire 1 S a [20] $end
$var wire 1 T a [19] $end
$var wire 1 U a [18] $end
$var wire 1 V a [17] $end
$var wire 1 W a [16] $end
$var wire 1 X a [15] $end
$var wire 1 Y a [14] $end
$var wire 1 Z a [13] $end
$var wire 1 [ a [12] $end
$var wire 1 \ a [11] $end
$var wire 1 ] a [10] $end
$var wire 1 ^ a [9] $end
$var wire 1 _ a [8] $end
$var wire 1 ` a [7] $end
$var wire 1 a a [6] $end
$var wire 1 b a [5] $end
$var wire 1 c a [4] $end
$var wire 1 d a [3] $end
$var wire 1 e a [2] $end
$var wire 1 f a [1] $end
$var wire 1 g a [0] $end
$var wire 1 h b [63] $end
$var wire 1 i b [62] $end
$var wire 1 j b [61] $end
$var wire 1 k b [60] $end
$var wire 1 l b [59] $end
$var wire 1 m b [58] $end
$var wire 1 n b [57] $end
$var wire 1 o b [56] $end
$var wire 1 p b [55] $end
$var wire 1 q b [54] $end
$var wire 1 r b [53] $end
$var wire 1 s b [52] $end
$var wire 1 t b [51] $end
$var wire 1 u b [50] $end
$var wire 1 v b [49] $end
$var wire 1 w b [48] $end
$var wire 1 x b [47] $end
$var wire 1 y b [46] $end
$var wire 1 z b [45] $end
$var wire 1 { b [44] $end
$var wire 1 | b [43] $end
$var wire 1 } b [42] $end
$var wire 1 ~ b [41] $end
$var wire 1 !! b [40] $end
$var wire 1 "! b [39] $end
$var wire 1 #! b [38] $end
$var wire 1 $! b [37] $end
$var wire 1 %! b [36] $end
$var wire 1 &! b [35] $end
$var wire 1 '! b [34] $end
$var wire 1 (! b [33] $end
$var wire 1 )! b [32] $end
$var wire 1 *! b [31] $end
$var wire 1 +! b [30] $end
$var wire 1 ,! b [29] $end
$var wire 1 -! b [28] $end
$var wire 1 .! b [27] $end
$var wire 1 /! b [26] $end
$var wire 1 0! b [25] $end
$var wire 1 1! b [24] $end
$var wire 1 2! b [23] $end
$var wire 1 3! b [22] $end
$var wire 1 4! b [21] $end
$var wire 1 5! b [20] $end
$var wire 1 6! b [19] $end
$var wire 1 7! b [18] $end
$var wire 1 8! b [17] $end
$var wire 1 9! b [16] $end
$var wire 1 :! b [15] $end
$var wire 1 ;! b [14] $end
$var wire 1 <! b [13] $end
$var wire 1 =! b [12] $end
$var wire 1 >! b [11] $end
$var wire 1 ?! b [10] $end
$var wire 1 @! b [9] $end
$var wire 1 A! b [8] $end
$var wire 1 B! b [7] $end
$var wire 1 C! b [6] $end
$var wire 1 D! b [5] $end
$var wire 1 E! b [4] $end
$var wire 1 F! b [3] $end
$var wire 1 G! b [2] $end
$var wire 1 H! b [1] $end
$var wire 1 I! b [0] $end
$var wire 1 ' gt $end
$var wire 1 & lt $end
$var wire 1 % eq $end
$var wire 1 $ ge $end
$var wire 1 # le $end
$upscope $end
$upscope $end
$enddefinitions $end
#0
$dumpvars
b10010000101010011010100100100 !
b1111111111111111111111111111111111000000100010010101111010000001 "
0'
1&
0%
0$
1#
0g
0f
1e
0d
0c
1b
0a
0`
1_
0^
1]
0\
1[
1Z
0Y
0X
1W
0V
1U
0T
1S
0R
0Q
0P
0O
1N
0M
0L
1K
0J
0I
0H
0G
0F
0E
0D
0C
0B
0A
0@
0?
0>
0=
0<
0;
0:
09
08
07
06
05
04
03
02
01
00
0/
0.
0-
0,
0+
0*
0)
0(
1I!
0H!
0G!
0F!
0E!
0D!
0C!
1B!
0A!
1@!
1?!
1>!
1=!
0<!
1;!
0:!
19!
08!
07!
16!
05!
04!
03!
12!
01!
00!
0/!
0.!
0-!
0,!
1+!
1*!
1)!
1(!
1'!
1&!
1%!
1$!
1#!
1"!
1!!
1~
1}
1|
1{
1z
1y
1x
1w
1v
1u
1t
1s
1r
1q
1p
1o
1n
1m
1l
1k
1j
1i
1h
$end
#5
b1111111111111111111111111111111110000100100001001101011000001001 !
b1111111111111111111111111111111110110001111100000101011001100011 "
1H!
1D!
1C!
0B!
0>!
09!
06!
15!
14!
13!
11!
1-!
1,!
0+!
1g
0e
1d
0b
0_
1^
0Z
1Y
1X
0W
0S
1P
0N
1M
0K
1H
1G
1F
1E
1D
1C
1B
1A
1@
1?
1>
1=
1<
1;
1:
19
18
17
16
15
14
13
12
11
10
1/
1.
1-
1,
1+
1*
1)
1(
#10
b110101110010111101100001101 !
b1000110110111111001100110001101 "
0H!
1G!
1F!
0D!
0C!
1B!
1A!
0@!
0?!
1>!
0;!
1:!
19!
18!
17!
16!
04!
01!
10!
1/!
0-!
0,!
1+!
0*!
0)!
0(!
0'!
0&!
0%!
0$!
0#!
0"!
0!!
0~
0}
0|
0{
0z
0y
0x
0w
0v
0u
0t
0s
0r
0q
0p
0o
0n
0m
0l
0k
0j
0i
0h
1e
1_
0]
1\
1Z
0X
1W
0U
1T
1S
1R
1N
0H
0G
0F
0E
0D
0C
0B
0A
0@
0?
0>
0=
0<
0;
0:
09
08
07
06
05
04
03
02
01
00
0/
0.
0-
0,
0+
0*
0)
0(
#15
b1111111111111111111111111111111110110010110000101000010001100101 !
b1111111111111111111111111111111110001001001101110101001000010010 "
0I!
1H!
0G!
0F!
1E!
0B!
0A!
1@!
0>!
1;!
0:!
06!
14!
03!
02!
11!
00!
0/!
1.!
0+!
1*!
1)!
1(!
1'!
1&!
1%!
1$!
1#!
1"!
1!!
1~
1}
1|
1{
1z
1y
1x
1w
1v
1u
1t
1s
1r
1q
1p
1o
1n
1m
1l
1k
1j
1i
1h
0d
1b
1a
0_
0^
1]
0\
0[
0Z
0Y
1X
0W
1V
0T
0S
0R
1Q
0M
1K
1J
1H
1G
1F
1E
1D
1C
1B
1A
1@
1?
1>
1=
1<
1;
1:
19
18
17
16
15
14
13
12
11
10
1/
1.
1-
1,
1+
1*
1)
1(
0#
1$
0&
1'
#20
b111100111110001100000001 !
b110110101111100110100001101 "
1I!
0H!
1G!
1F!
0E!
1A!
0@!
1?!
1>!
0=!
1:!
04!
13!
12!
01!
10!
1/!
0.!
0*!
0)!
0(!
0'!
0&!
0%!
0$!
0#!
0"!
0!!
0~
0}
0|
0{
0z
0y
0x
0w
0v
0u
0t
0s
0r
0q
0p
0o
0n
0m
0l
0k
0j
0i
0h
0e
0b
0a
1_
1^
0]
1Z
1Y
1W
1S
1R
0N
0K
0J
0H
0G
0F
0E
0D
0C
0B
0A
0@
0?
0>
0=
0<
0;
0:
09
08
07
06
05
04
03
02
01
00
0/
0.
0-
0,
0+
0*
0)
0(
1#
0$
1&
0'
#25
b111011001000111111000101110110 !
b11110100011011100110100111101 "
1E!
1D!
08!
16!
05!
03!
1.!
1-!
0g
1f
1e
1c
1b
1a
0^
1[
0S
0Q
0P
1O
1N
1L
1K
1J
0#
1$
0&
1'
#30
b1110110110101000101011111101101 !
b1000110001011011111011110001100 "
0I!
0E!
0D!
1B!
1@!
0>!
1=!
1<!
14!
02!
0.!
0-!
1+!
1g
0f
1d
0c
1`
1^
1]
0Z
0X
0W
0V
1U
1S
0R
1Q
1P
0O
1M
0L
1I
#35
b1111100111111011110100111111001 !
b1111111111111111111111111111111111100011001101110010010011000110 "
1H!
0F!
1C!
0A!
0@!
0=!
0;!
0:!
18!
06!
15!
11!
0/!
1,!
1*!
1)!
1(!
1'!
1&!
1%!
1$!
1#!
1"!
1!!
1~
1}
1|
1{
1z
1y
1x
1w
1v
1u
1t
1s
1r
1q
1p
1o
1n
1m
1l
1k
1j
1i
1h
0e
1c
0^
0]
1\
0[
1Z
1X
1W
1T
1R
0N
1L
1#
0$
1&
0'
#40
b1111111111111111111111111111111111100010111101111000010011000101 !
b1111111111111111111111111111111111010101000100111101001010101010 "
0G!
1F!
1D!
0C!
1@!
0?!
1=!
0<!
1;!
1:!
07!
04!
00!
1/!
1-!
0,!
1e
0d
0c
0b
0_
1]
0\
0Z
0Y
1V
0T
1N
0M
0L
0K
1H
1G
1F
1E
1D
1C
1B
1A
1@
1?
1>
1=
1<
1;
1:
19
18
17
16
15
14
13
12
11
10
1/
1.
1-
1,
1+
1*
1)
1(
0#
1$
0&
1'
#45
b1110010101011111111011111100101 !
b1111111111111111111111111111111110111011110100100111001001110111 "
1I!
1G!
0F!
1E!
1C!
0B!
1<!
0:!
09!
13!
12!
10!
0/!
1.!
1,!
0+!
1b
1_
1^
1[
1Z
1Y
1T
0S
0Q
1K
0H
0G
0F
0E
0D
0C
0B
0A
0@
0?
0>
0=
0<
0;
0:
09
08
07
06
05
04
03
02
01
00
0/
0.
0-
0,
0+
0*
0)
0(
1#
0$
1&
0'
#50
b1111111111111111111111111111111110001001001100101101011000010010 !
b1000111111011001101101110001111 "
1F!
0E!
0D!
0C!
1B!
1A!
1>!
0<!
1:!
08!
17!
16!
05!
14!
1/!
0.!
0-!
0,!
1+!
0*!
0)!
0(!
0'!
0&!
0%!
0$!
0#!
0"!
0!!
0~
0}
0|
0{
0z
0y
0x
0w
0v
0u
0t
0s
0r
0q
0p
0o
0n
0m
0l
0k
0j
0i
0h
0g
1f
0e
1c
0b
0a
0`
0_
0Z
0W
0U
0T
1S
0P
1O
0N
1L
0K
0J
0I
1H
1G
1F
1E
1D
1C
1B
1A
1@
1?
1>
1=
1<
1;
1:
19
18
17
16
15
14
13
12
11
10
1/
1.
1-
1,
1+
1*
1)
1(
0#
1$
0&
1'
#55
b1111001001100000110100111110010 !
b1111111111111111111111111111111111100111011101101001011011001110 "
0I!
1C!
0A!
1?!
0>!
0;!
18!
06!
15!
02!
1,!
1*!
1)!
1(!
1'!
1&!
1%!
1$!
1#!
1"!
1!!
1~
1}
1|
1{
1z
1y
1x
1w
1v
1u
1t
1s
1r
1q
1p
1o
1n
1m
1l
1k
1j
1i
1h
1b
1a
1`
1_
0^
0]
1\
0[
1Z
0X
0V
1K
1J
1I
0H
0G
0F
0E
0D
0C
0B
0A
0@
0?
0>
0=
0<
